pyjn/__init__.py
pyjn/pyjn.py
pyjn-0.0.1.dist-info/LICENSE.txt
pyjn-0.0.1.dist-info/METADATA
pyjn-0.0.1.dist-info/WHEEL
pyjn-0.0.1.dist-info/top_level.txt
pyjn-0.0.1.dist-info/RECORD
