Metadata-Version: 2.1
Name: pyjn
Version: 0.0.1
Summary: JSON Ref Resolver for standard JSON Schema with Max and Min Schema Generation
Home-page: https://github.com/deepstartup/pyjn
Author: Arghadeep Chaudhury,Siddhartha Bhattacharya
Author-email: arghadeep.chaudhury@gmail.com,siddbhatt@gmail.com
License: UNKNOWN
Platform: UNKNOWN
Classifier: Programming Language :: Python :: 3
Classifier: License :: OSI Approved :: MIT License
Classifier: Operating System :: OS Independent
Requires-Dist: flatten-json
